pyexplorer/__init__.py
pyexplorer/__main__.py
pyexplorer/discovery.py
pyexplorer/extract.py
pyexplorer/filters.py
pyexplorer/formatters.py
pyexplorer/interactive.py
pyexplorer/utilities.py
pyexplorer-0.1a1.dist-info/METADATA
pyexplorer-0.1a1.dist-info/RECORD
pyexplorer-0.1a1.dist-info/WHEEL
pyexplorer-0.1a1.dist-info/entry_points.txt
pyexplorer-0.1a1.dist-info/top_level.txt
