Metadata-Version: 2.1
Name: pyexplorer
Version: 0.1a1
Summary: Explore python modules interactively.
Home-page: https://github.com/dexpota/pyexplorer
Author: Fabrizio Destro
Author-email: destro.fabrizio@gmail.com
License: UNKNOWN
Platform: UNKNOWN
Classifier: Development Status :: 3 - Alpha
Classifier: Intended Audience :: Developers
Classifier: Programming Language :: Python :: 2
Classifier: Programming Language :: Python :: 3
Requires-Dist: termcolor
Requires-Dist: prompt-toolkit
Requires-Dist: future
